{"ExplicitlyFormattedLogicalRecords": [{"FhlrEFLR": {"setName": null, "setType": "FILE-HEADER", "template": {"attributeList": [{"_label": "SEQUENCE-NUMBER", "_count": 1, "_repCode": 20, "_units": "", "_value": null}, {"_label": "ID", "_count": 1, "_repCode": 20, "_units": "", "_value": null}]}, "objects": [{"FileHeader": {"_name": {"origin": 11, "copy": 0, "identifier": "0"}, "_attributes": [{"_label": "SEQUENCE-NUMBER", "_count": 1, "_repCode": 20, "_units": "", "_value": "         1"}, {"_label": "ID", "_count": 1, "_repCode": 20, "_units": "", "_value": "DEFAULT FHLR                                                     "}]}}]}}, {"OlrEFLR": {"setName": "OGR SET NAME", "setType": "ORIGIN", "template": {"attributeList": [{"_label": "FILE-ID", "_count": 1, "_repCode": 20, "_units": "", "_value": null}, {"_label": "FILE-SET-NAME", "_count": 1, "_repCode": 19, "_units": "", "_value": null}, {"_label": "FILE-SET-NUMBER", "_count": 1, "_repCode": 18, "_units": "", "_value": null}, {"_label": "FILE-NUMBER", "_count": 1, "_repCode": 18, "_units": "", "_value": null}, {"_label": "FILE-TYPE", "_count": 1, "_repCode": 19, "_units": "", "_value": null}, {"_label": "PRODUCT", "_count": 1, "_repCode": 20, "_units": "", "_value": null}, {"_label": "VERSION", "_count": 1, "_repCode": 20, "_units": "", "_value": null}, {"_label": "PROGRAMS", "_count": 1, "_repCode": 20, "_units": "", "_value": null}, {"_label": "CREATION-TIME", "_count": 1, "_repCode": 21, "_units": "", "_value": null}, {"_label": "ORDER-NUMBER", "_count": 1, "_repCode": 20, "_units": "", "_value": null}, {"_label": "DESCENT-NUMBER", "_count": 1, "_repCode": 20, "_units": "", "_value": null}, {"_label": "RUN-NUMBER", "_count": 1, "_repCode": 20, "_units": "", "_value": null}, {"_label": "WELL-ID", "_count": 1, "_repCode": 18, "_units": "", "_value": null}, {"_label": "WELL-NAME", "_count": 1, "_repCode": 20, "_units": "", "_value": null}, {"_label": "FIELD-NAME", "_count": 1, "_repCode": 20, "_units": "", "_value": null}, {"_label": "PRODUCER-CODE", "_count": 1, "_repCode": 16, "_units": "", "_value": null}, {"_label": "PRODUCER-NAME", "_count": 1, "_repCode": 20, "_units": "", "_value": null}, {"_label": "COMPANY", "_count": 1, "_repCode": 20, "_units": "", "_value": null}, {"_label": "NAME-SPACE-NAME", "_count": 1, "_repCode": 19, "_units": "", "_value": null}, {"_label": "NAME-SPACE-VERSION", "_count": 1, "_repCode": 18, "_units": "", "_value": null}]}, "objects": [{"Origin": {"_name": {"origin": 11, "copy": 0, "identifier": "DEFINING ORIGIN"}, "_attributes": [{"_label": "FILE-ID", "_count": 1, "_repCode": 20, "_units": "", "_value": "AQLN file_id"}, {"_label": "FILE-SET-NAME", "_count": 1, "_repCode": 19, "_units": "", "_value": "AQLN file_set_name"}, {"_label": "FILE-SET-NUMBER", "_count": 1, "_repCode": 18, "_units": "", "_value": 11}, {"_label": "FILE-NUMBER", "_count": 1, "_repCode": 18, "_units": "", "_value": 22}, {"_label": "FILE-TYPE", "_count": 1, "_repCode": 19, "_units": "", "_value": "AQLN file_type"}, {"_label": "PRODUCT", "_count": 1, "_repCode": 20, "_units": "", "_value": "AQLN product"}, {"_label": "VERSION", "_count": 1, "_repCode": 20, "_units": "", "_value": "AQLN version"}, {"_label": "PROGRAMS", "_count": 1, "_repCode": 20, "_units": "", "_value": "AQLN programs"}, {"_label": "CREATION-TIME", "_count": 1, "_repCode": 21, "_units": "", "_value": {"time": "2022-09-06 19:08:33.958000", "tzone": {"timezone": "LocalStandard"}}}, {"_label": "ORDER-NUMBER", "_count": 1, "_repCode": 20, "_units": "", "_value": "AQLN order_number"}, {"_label": "DESCENT-NUMBER", "_count": 1, "_repCode": 20, "_units": "", "_value": "33"}, {"_label": "RUN-NUMBER", "_count": 1, "_repCode": 20, "_units": "", "_value": "44"}, {"_label": "WELL-ID", "_count": 1, "_repCode": 18, "_units": "", "_value": 55}, {"_label": "WELL-NAME", "_count": 1, "_repCode": 20, "_units": "", "_value": "AQLN well_name"}, {"_label": "FIELD-NAME", "_count": 1, "_repCode": 20, "_units": "", "_value": "AQLN field_name"}, {"_label": "PRODUCER-CODE", "_count": 1, "_repCode": 16, "_units": "", "_value": 1}, {"_label": "PRODUCER-NAME", "_count": 1, "_repCode": 20, "_units": "", "_value": "AQLN producer_name"}, {"_label": "COMPANY", "_count": 1, "_repCode": 20, "_units": "", "_value": "AQLN company"}, {"_label": "NAME-SPACE-NAME", "_count": 1, "_repCode": 19, "_units": "", "_value": "AQLN name_space_name"}, {"_label": "NAME-SPACE-VERSION", "_count": 1, "_repCode": 18, "_units": "", "_value": 66}]}}]}}, null, {"ChannelEFLR": {"setName": null, "setType": "CHANNEL", "template": {"attributeList": [{"_label": "LONG-NAME", "_count": 1, "_repCode": 20, "_units": "", "_value": null}, {"_label": "PROPERTIES", "_count": 1, "_repCode": 19, "_units": "", "_value": null}, {"_label": "REPRESENTATION-CODE", "_count": 1, "_repCode": 15, "_units": "", "_value": null}, {"_label": "UNITS", "_count": 1, "_repCode": 27, "_units": "", "_value": null}, {"_label": "DIMENSION", "_count": 1, "_repCode": 18, "_units": "", "_value": null}, {"_label": "AXIS", "_count": 1, "_repCode": 23, "_units": "", "_value": null}, {"_label": "ELEMENT-LIMIT", "_count": 1, "_repCode": 18, "_units": "", "_value": null}, {"_label": "SOURCE", "_count": 1, "_repCode": 24, "_units": "", "_value": null}]}, "objects": [{"Channel": {"_name": {"origin": 11, "copy": 0, "identifier": "DEPTH CHANNEL"}, "_attributes": [{"_label": "LONG-NAME", "_count": 1, "_repCode": 20, "_units": "", "_value": "DEPTH"}, {"_label": "PROPERTIES", "_count": 2, "_repCode": 19, "_units": "", "_value": ["0309 AQLN PROP 1", "PROP AQLN 2"]}, {"_label": "REPRESENTATION-CODE", "_count": 1, "_repCode": 15, "_units": "", "_value": 7}, {"_label": "UNITS", "_count": 1, "_repCode": 27, "_units": "", "_value": "m"}, {"_label": "DIMENSION", "_count": 1, "_repCode": 18, "_units": "", "_value": 1}, {"_label": "AXIS", "_count": 1, "_repCode": 23, "_units": "", "_value": null}, {"_label": "ELEMENT-LIMIT", "_count": 1, "_repCode": 18, "_units": "", "_value": 1}, {"_label": "SOURCE", "_count": 1, "_repCode": 24, "_units": "", "_value": null}]}}, {"Channel": {"_name": {"origin": 11, "copy": 0, "identifier": "CURVE 1 CHANNEL"}, "_attributes": [{"_label": "LONG-NAME", "_count": 1, "_repCode": 20, "_units": "", "_value": "CURVE 1"}, {"_label": "PROPERTIES", "_count": 1, "_repCode": 19, "_units": "", "_value": null}, {"_label": "REPRESENTATION-CODE", "_count": 1, "_repCode": 15, "_units": "", "_value": 7}, {"_label": "UNITS", "_count": 1, "_repCode": 27, "_units": "", "_value": "t"}, {"_label": "DIMENSION", "_count": 1, "_repCode": 18, "_units": "", "_value": 1}, {"_label": "AXIS", "_count": 1, "_repCode": 23, "_units": "", "_value": null}, {"_label": "ELEMENT-LIMIT", "_count": 1, "_repCode": 18, "_units": "", "_value": 1}, {"_label": "SOURCE", "_count": 1, "_repCode": 24, "_units": "", "_value": null}]}}, {"Channel": {"_name": {"origin": 11, "copy": 0, "identifier": "CURVE 2 CHANNEL"}, "_attributes": [{"_label": "LONG-NAME", "_count": 1, "_repCode": 20, "_units": "", "_value": "CURVE 2"}, {"_label": "PROPERTIES", "_count": 1, "_repCode": 19, "_units": "", "_value": null}, {"_label": "REPRESENTATION-CODE", "_count": 1, "_repCode": 15, "_units": "", "_value": 7}, {"_label": "UNITS", "_count": 1, "_repCode": 27, "_units": "", "_value": "t"}, {"_label": "DIMENSION", "_count": 1, "_repCode": 18, "_units": "", "_value": 1}, {"_label": "AXIS", "_count": 1, "_repCode": 23, "_units": "", "_value": null}, {"_label": "ELEMENT-LIMIT", "_count": 1, "_repCode": 18, "_units": "", "_value": 1}, {"_label": "SOURCE", "_count": 1, "_repCode": 24, "_units": "", "_value": null}]}}]}}, {"FrameEFLR": {"setName": null, "setType": "FRAME", "template": {"attributeList": [{"_label": "CHANNELS", "_count": 1, "_repCode": 23, "_units": "", "_value": null}, {"_label": "INDEX-TYPE", "_count": 1, "_repCode": 19, "_units": "", "_value": null}, {"_label": "SPACING", "_count": 1, "_repCode": 7, "_units": "", "_value": null}]}, "objects": [{"Frame": {"_name": {"origin": 11, "copy": 0, "identifier": "MAIN"}, "_attributes": [{"_label": "CHANNELS", "_count": 3, "_repCode": 23, "_units": "", "_value": [{"origin": 11, "copy": 0, "identifier": "DEPTH CHANNEL"}, {"origin": 11, "copy": 0, "identifier": "CURVE 1 CHANNEL"}, {"origin": 11, "copy": 0, "identifier": "CURVE 2 CHANNEL"}]}, {"_label": "INDEX-TYPE", "_count": 1, "_repCode": 19, "_units": "", "_value": "BOREHOLE-DEPTH"}, {"_label": "SPACING", "_count": 1, "_repCode": 7, "_units": "m", "_value": 0.33}]}}]}}, {"StaticEFLR": {"setName": null, "setType": "ZONE", "template": {"attributeList": [{"_label": "DESCRIPTION", "_count": 1, "_repCode": 20, "_units": "", "_value": null}, {"_label": "DOMAIN", "_count": 1, "_repCode": 19, "_units": "", "_value": null}, {"_label": "MAXIMUM", "_count": 1, "_repCode": 7, "_units": "", "_value": null}, {"_label": "MINIMUM", "_count": 1, "_repCode": 7, "_units": "", "_value": null}]}, "objects": [{"Zone": {"_name": {"origin": 11, "copy": 0, "identifier": "DEPTH ZONE OBJ"}, "_attributes": [{"_label": "DESCRIPTION", "_count": 1, "_repCode": 20, "_units": "", "_value": "DEPTH ZONE"}, {"_label": "DOMAIN", "_count": 1, "_repCode": 19, "_units": "", "_value": "BOREHOLE-DEPTH"}, {"_label": "MAXIMUM", "_count": 1, "_repCode": 7, "_units": "m", "_value": 922.98}, {"_label": "MINIMUM", "_count": 1, "_repCode": 7, "_units": "m", "_value": 10.42}]}}]}}, {"StaticEFLR": {"setName": null, "setType": "ZONE", "template": {"attributeList": [{"_label": "DESCRIPTION", "_count": 1, "_repCode": 20, "_units": "", "_value": null}, {"_label": "DOMAIN", "_count": 1, "_repCode": 19, "_units": "", "_value": null}, {"_label": "MAXIMUM", "_count": 1, "_repCode": 21, "_units": "", "_value": null}, {"_label": "MINIMUM", "_count": 1, "_repCode": 21, "_units": "", "_value": null}]}, "objects": [{"Zone": {"_name": {"origin": 11, "copy": 0, "identifier": "TIME -ZONE OBJ"}, "_attributes": [{"_label": "DESCRIPTION", "_count": 1, "_repCode": 20, "_units": "", "_value": "TIME"}, {"_label": "DOMAIN", "_count": 1, "_repCode": 19, "_units": "", "_value": "TIME"}, {"_label": "MAXIMUM", "_count": 1, "_repCode": 21, "_units": "", "_value": {"time": "2022-08-05 16:00:00", "tzone": {"timezone": "LocalStandard"}}}, {"_label": "MINIMUM", "_count": 1, "_repCode": 21, "_units": "", "_value": {"time": "2022-08-05 09:00:00", "tzone": {"timezone": "LocalStandard"}}}]}}]}}, {"StaticEFLR": {"setName": null, "setType": "PARAMETER", "template": {"attributeList": [{"_label": "LONG-NAME", "_count": 1, "_repCode": 20, "_units": "", "_value": null}, {"_label": "DIMENSION", "_count": 1, "_repCode": 18, "_units": "", "_value": null}, {"_label": "AXIS", "_count": 1, "_repCode": 23, "_units": "", "_value": null}, {"_label": "ZONES", "_count": 1, "_repCode": 23, "_units": "", "_value": null}, {"_label": "VALUES", "_count": 1, "_repCode": 19, "_units": "", "_value": null}]}, "objects": [{"Parameter": {"_name": {"origin": 11, "copy": 0, "identifier": "parameter_1-OBJ-NAME"}, "_attributes": [{"_label": "LONG-NAME", "_count": 1, "_repCode": 20, "_units": "", "_value": "LAT"}, {"_label": "DIMENSION", "_count": 1, "_repCode": 18, "_units": "", "_value": 1}, {"_label": "AXIS", "_count": 1, "_repCode": 23, "_units": "", "_value": null}, {"_label": "ZONES", "_count": 2, "_repCode": 23, "_units": "", "_value": [{"origin": 11, "copy": 0, "identifier": "DEPTH ZONE OBJ"}, {"origin": 11, "copy": 0, "identifier": "TIME -ZONE OBJ"}]}, {"_label": "VALUES", "_count": 2, "_repCode": 20, "_units": "", "_value": ["40deg 23' 42.8676'' N", "40deg 23' 42.8676'' N"]}]}}, {"Parameter": {"_name": {"origin": 11, "copy": 0, "identifier": "parameter_2-OBJ-NAME"}, "_attributes": [{"_label": "LONG-NAME", "_count": 1, "_repCode": 20, "_units": "", "_value": "LON"}, {"_label": "DIMENSION", "_count": 1, "_repCode": 18, "_units": "", "_value": 1}, {"_label": "AXIS", "_count": 1, "_repCode": 23, "_units": "", "_value": null}, {"_label": "ZONES", "_count": 1, "_repCode": 23, "_units": "", "_value": {"origin": 11, "copy": 0, "identifier": "DEPTH ZONE OBJ"}}, {"_label": "VALUES", "_count": 1, "_repCode": 20, "_units": "", "_value": "27deg 47' 32.8956'' E"}]}}, {"Parameter": {"_name": {"origin": 11, "copy": 0, "identifier": "parameter_3-OBJ-NAME"}, "_attributes": [{"_label": "LONG-NAME", "_count": 1, "_repCode": 20, "_units": "", "_value": "SOME-FLOAT-PARAM"}, {"_label": "DIMENSION", "_count": 1, "_repCode": 18, "_units": "", "_value": 1}, {"_label": "AXIS", "_count": 1, "_repCode": 23, "_units": "", "_value": null}, {"_label": "ZONES", "_count": 1, "_repCode": 23, "_units": "", "_value": null}, {"_label": "VALUES", "_count": 1, "_repCode": 7, "_units": "m", "_value": 2378.1312}]}}]}}, {"StaticEFLR": {"setName": null, "setType": "EQUIPMENT", "template": {"attributeList": [{"_label": "TRADEMARK-NAME", "_count": 1, "_repCode": 19, "_units": "", "_value": null}, {"_label": "STATUS", "_count": 1, "_repCode": 19, "_units": "", "_value": null}, {"_label": "TYPE", "_count": 1, "_repCode": 19, "_units": "", "_value": null}, {"_label": "SERIAL-NUMBER", "_count": 1, "_repCode": 19, "_units": "", "_value": null}, {"_label": "LOCATION", "_count": 1, "_repCode": 19, "_units": "", "_value": null}, {"_label": "HEIGHT", "_count": 1, "_repCode": 19, "_units": "", "_value": null}, {"_label": "LENGTH", "_count": 1, "_repCode": 19, "_units": "", "_value": null}, {"_label": "MINIMUM-DIAMETER", "_count": 1, "_repCode": 19, "_units": "", "_value": null}, {"_label": "MAXIMUM-DIAMETER", "_count": 1, "_repCode": 19, "_units": "", "_value": null}, {"_label": "VOLUME", "_count": 1, "_repCode": 19, "_units": "", "_value": null}, {"_label": "WEIGHT", "_count": 1, "_repCode": 19, "_units": "", "_value": null}, {"_label": "HOLE-SIZE", "_count": 1, "_repCode": 19, "_units": "", "_value": null}, {"_label": "PRESSURE", "_count": 1, "_repCode": 19, "_units": "", "_value": null}, {"_label": "TEMPERATURE", "_count": 1, "_repCode": 19, "_units": "", "_value": null}, {"_label": "VERTICAL-DEPTH", "_count": 1, "_repCode": 19, "_units": "", "_value": null}, {"_label": "RADIAL-DRIFT", "_count": 1, "_repCode": 19, "_units": "", "_value": null}, {"_label": "ANGULAR-DRIFT", "_count": 1, "_repCode": 19, "_units": "", "_value": null}]}, "objects": [{"Equipment": {"_name": {"origin": 11, "copy": 0, "identifier": "SOME_EQPMNT"}, "_attributes": [{"_label": "TRADEMARK-NAME", "_count": 1, "_repCode": 20, "_units": "", "_value": "EQ-TRADEMARKNAME"}, {"_label": "STATUS", "_count": 1, "_repCode": 26, "_units": "", "_value": 1}, {"_label": "TYPE", "_count": 1, "_repCode": 19, "_units": "", "_value": "Tool"}, {"_label": "SERIAL-NUMBER", "_count": 1, "_repCode": 19, "_units": "", "_value": "9101-21391"}, {"_label": "LOCATION", "_count": 1, "_repCode": 19, "_units": "", "_value": "Well"}, {"_label": "HEIGHT", "_count": 1, "_repCode": 2, "_units": "in", "_value": 140.0}, {"_label": "LENGTH", "_count": 1, "_repCode": 2, "_units": "cm", "_value": 230.77999877929688}, {"_label": "MINIMUM-DIAMETER", "_count": 1, "_repCode": 2, "_units": "m", "_value": 2.299999952316284}, {"_label": "MAXIMUM-DIAMETER", "_count": 1, "_repCode": 2, "_units": "3.2", "_value": 3.200000047683716}, {"_label": "VOLUME", "_count": 1, "_repCode": 2, "_units": "cm3", "_value": 100.0}, {"_label": "WEIGHT", "_count": 1, "_repCode": 2, "_units": "t", "_value": 1.2000000476837158}, {"_label": "HOLE-SIZE", "_count": 1, "_repCode": 2, "_units": "m", "_value": 323.20001220703125}, {"_label": "PRESSURE", "_count": 1, "_repCode": 2, "_units": "psi", "_value": 18000.0}, {"_label": "TEMPERATURE", "_count": 1, "_repCode": 2, "_units": "degC", "_value": 24.0}, {"_label": "VERTICAL-DEPTH", "_count": 1, "_repCode": 2, "_units": "m", "_value": 587.0}, {"_label": "RADIAL-DRIFT", "_count": 1, "_repCode": 2, "_units": "m", "_value": 23.219999313354492}, {"_label": "ANGULAR-DRIFT", "_count": 1, "_repCode": 2, "_units": "m", "_value": 32.5}]}}]}}, {"StaticEFLR": {"setName": null, "setType": "TOOL", "template": {"attributeList": [{"_label": "DESCRIPTION", "_count": 1, "_repCode": 20, "_units": "", "_value": null}, {"_label": "TRADEMARK-NAME", "_count": 1, "_repCode": 20, "_units": "", "_value": null}, {"_label": "GENERIC-NAME", "_count": 1, "_repCode": 20, "_units": "", "_value": null}, {"_label": "PARTS", "_count": 1, "_repCode": 23, "_units": "", "_value": null}, {"_label": "STATUS", "_count": 1, "_repCode": 26, "_units": "", "_value": null}, {"_label": "CHANNELS", "_count": 1, "_repCode": 23, "_units": "", "_value": null}, {"_label": "PARAMETERS", "_count": 1, "_repCode": 23, "_units": "", "_value": null}]}, "objects": [{"Tool": {"_name": {"origin": 11, "copy": 0, "identifier": "FIRST TOOL"}, "_attributes": [{"_label": "DESCRIPTION", "_count": 1, "_repCode": 20, "_units": "", "_value": "TOOL 1"}, {"_label": "TRADEMARK-NAME", "_count": 1, "_repCode": 20, "_units": "", "_value": "AQLN TOOL 1"}, {"_label": "GENERIC-NAME", "_count": 1, "_repCode": 20, "_units": "", "_value": "SOME TOOL"}, {"_label": "PARTS", "_count": 1, "_repCode": 23, "_units": "", "_value": {"origin": 11, "copy": 0, "identifier": "SOME_EQPMNT"}}, {"_label": "STATUS", "_count": 1, "_repCode": 26, "_units": "", "_value": 1}, {"_label": "CHANNELS", "_count": 2, "_repCode": 23, "_units": "", "_value": [{"origin": 11, "copy": 0, "identifier": "CURVE 1 CHANNEL"}, {"origin": 11, "copy": 0, "identifier": "CURVE 2 CHANNEL"}]}, {"_label": "PARAMETERS", "_count": 2, "_repCode": 23, "_units": "", "_value": [{"origin": 11, "copy": 0, "identifier": "parameter_1-OBJ-NAME"}, {"origin": 11, "copy": 0, "identifier": "parameter_2-OBJ-NAME"}]}]}}, {"Tool": {"_name": {"origin": 11, "copy": 0, "identifier": "DEPTH TOOL"}, "_attributes": [{"_label": "DESCRIPTION", "_count": 1, "_repCode": 20, "_units": "", "_value": "TOOL for DEPTH"}, {"_label": "TRADEMARK-NAME", "_count": 1, "_repCode": 20, "_units": "", "_value": "AQLN DEPTH TOOL"}, {"_label": "GENERIC-NAME", "_count": 1, "_repCode": 20, "_units": "", "_value": "SOME TOOL for DEPTH"}, {"_label": "PARTS", "_count": 1, "_repCode": 23, "_units": "", "_value": {"origin": 11, "copy": 0, "identifier": "SOME_EQPMNT"}}, {"_label": "STATUS", "_count": 1, "_repCode": 26, "_units": "", "_value": 1}, {"_label": "CHANNELS", "_count": 1, "_repCode": 23, "_units": "", "_value": {"origin": 11, "copy": 0, "identifier": "DEPTH CHANNEL"}}, {"_label": "PARAMETERS", "_count": 2, "_repCode": 23, "_units": "", "_value": [{"origin": 11, "copy": 0, "identifier": "parameter_1-OBJ-NAME"}, {"origin": 11, "copy": 0, "identifier": "parameter_2-OBJ-NAME"}]}]}}]}}, {"StaticEFLR": {"setName": null, "setType": "COMPUTATION", "template": {"attributeList": [{"_label": "LONG-NAME", "_count": 1, "_repCode": 20, "_units": "", "_value": null}, {"_label": "PROPERTIES", "_count": 1, "_repCode": 19, "_units": "", "_value": null}, {"_label": "DIMENSION", "_count": 1, "_repCode": 18, "_units": "", "_value": null}, {"_label": "AXIS", "_count": 1, "_repCode": 23, "_units": "", "_value": null}, {"_label": "ZONES", "_count": 1, "_repCode": 23, "_units": "", "_value": null}, {"_label": "VALUES", "_count": 1, "_repCode": 19, "_units": "", "_value": null}, {"_label": "SOURCE", "_count": 1, "_repCode": 19, "_units": "", "_value": null}]}, "objects": [{"Computation": {"_name": {"origin": 11, "copy": 0, "identifier": "computation_1 OBJ NAME"}, "_attributes": [{"_label": "LONG-NAME", "_count": 1, "_repCode": 20, "_units": "", "_value": "Average"}, {"_label": "PROPERTIES", "_count": 1, "_repCode": 19, "_units": "", "_value": "AVERAGED"}, {"_label": "DIMENSION", "_count": 1, "_repCode": 18, "_units": "", "_value": 1}, {"_label": "AXIS", "_count": 1, "_repCode": 23, "_units": "", "_value": null}, {"_label": "ZONES", "_count": 2, "_repCode": 23, "_units": "", "_value": [{"origin": 11, "copy": 0, "identifier": "DEPTH ZONE OBJ"}, {"origin": 11, "copy": 0, "identifier": "TIME -ZONE OBJ"}]}, {"_label": "VALUES", "_count": 2, "_repCode": 7, "_units": "m", "_value": [112.124, 42.23]}, {"_label": "SOURCE", "_count": 1, "_repCode": 19, "_units": "", "_value": null}]}}, {"Computation": {"_name": {"origin": 11, "copy": 0, "identifier": "computation_2 OBJ NAME"}, "_attributes": [{"_label": "LONG-NAME", "_count": 1, "_repCode": 20, "_units": "", "_value": "Normalization"}, {"_label": "PROPERTIES", "_count": 2, "_repCode": 19, "_units": "", "_value": ["NORMALIZED", "AVERAGED"]}, {"_label": "DIMENSION", "_count": 1, "_repCode": 18, "_units": "", "_value": 1}, {"_label": "AXIS", "_count": 1, "_repCode": 23, "_units": "", "_value": null}, {"_label": "ZONES", "_count": 2, "_repCode": 23, "_units": "", "_value": [{"origin": 11, "copy": 0, "identifier": "DEPTH ZONE OBJ"}, {"origin": 11, "copy": 0, "identifier": "TIME -ZONE OBJ"}]}, {"_label": "VALUES", "_count": 2, "_repCode": 7, "_units": "m", "_value": [0.876, 0.564]}, {"_label": "SOURCE", "_count": 1, "_repCode": 19, "_units": "", "_value": null}]}}]}}, {"StaticEFLR": {"setName": null, "setType": "PROCESS", "template": {"attributeList": [{"_label": "DESCRIPTION", "_count": 1, "_repCode": 20, "_units": "", "_value": null}, {"_label": "TRADEMARK-NAME", "_count": 1, "_repCode": 20, "_units": "", "_value": null}, {"_label": "VERSION", "_count": 1, "_repCode": 20, "_units": "", "_value": null}, {"_label": "PROPERTIES", "_count": 1, "_repCode": 19, "_units": "", "_value": null}, {"_label": "STATUS", "_count": 1, "_repCode": 19, "_units": "", "_value": null}, {"_label": "INPUT-CHANNELS", "_count": 1, "_repCode": 23, "_units": "", "_value": null}, {"_label": "OUTPUT-CHANNELS", "_count": 1, "_repCode": 23, "_units": "", "_value": null}, {"_label": "INPUT-COMPUTATIONS", "_count": 1, "_repCode": 23, "_units": "", "_value": null}, {"_label": "OUTPUT-COMPUTATIONS", "_count": 1, "_repCode": 23, "_units": "", "_value": null}, {"_label": "PARAMETERS", "_count": 1, "_repCode": 23, "_units": "", "_value": null}, {"_label": "COMMENTS", "_count": 1, "_repCode": 20, "_units": "", "_value": null}]}, "objects": [{"Process": {"_name": {"origin": 11, "copy": 0, "identifier": "PROC-1 OBJ-NAME"}, "_attributes": [{"_label": "DESCRIPTION", "_count": 1, "_repCode": 20, "_units": "", "_value": "Process 1"}, {"_label": "TRADEMARK-NAME", "_count": 1, "_repCode": 20, "_units": "", "_value": "Proc 1 TMN"}, {"_label": "VERSION", "_count": 1, "_repCode": 20, "_units": "", "_value": "1.0.0"}, {"_label": "PROPERTIES", "_count": 1, "_repCode": 19, "_units": "", "_value": "NOPROP"}, {"_label": "STATUS", "_count": 1, "_repCode": 19, "_units": "", "_value": "COMPLETE"}, {"_label": "INPUT-CHANNELS", "_count": 1, "_repCode": 23, "_units": "", "_value": {"origin": 11, "copy": 0, "identifier": "DEPTH CHANNEL"}}, {"_label": "OUTPUT-CHANNELS", "_count": 1, "_repCode": 23, "_units": "", "_value": {"origin": 11, "copy": 0, "identifier": "CURVE 1 CHANNEL"}}, {"_label": "INPUT-COMPUTATIONS", "_count": 1, "_repCode": 23, "_units": "", "_value": {"origin": 11, "copy": 0, "identifier": "computation_1 OBJ NAME"}}, {"_label": "OUTPUT-COMPUTATIONS", "_count": 1, "_repCode": 23, "_units": "", "_value": {"origin": 11, "copy": 0, "identifier": "computation_2 OBJ NAME"}}, {"_label": "PARAMETERS", "_count": 3, "_repCode": 23, "_units": "", "_value": [{"origin": 11, "copy": 0, "identifier": "parameter_1-OBJ-NAME"}, {"origin": 11, "copy": 0, "identifier": "parameter_2-OBJ-NAME"}, {"origin": 11, "copy": 0, "identifier": "parameter_3-OBJ-NAME"}]}, {"_label": "COMMENTS", "_count": 1, "_repCode": 20, "_units": "", "_value": "These are dummy values for testing"}]}}, {"Process": {"_name": {"origin": 11, "copy": 0, "identifier": "PROC-2 OBJ-NAME"}, "_attributes": [{"_label": "DESCRIPTION", "_count": 1, "_repCode": 20, "_units": "", "_value": "Process 2"}, {"_label": "TRADEMARK-NAME", "_count": 1, "_repCode": 20, "_units": "", "_value": "Proc 2 TMN"}, {"_label": "VERSION", "_count": 1, "_repCode": 20, "_units": "", "_value": "2.0.0"}, {"_label": "PROPERTIES", "_count": 1, "_repCode": 19, "_units": "", "_value": "AVERAGED"}, {"_label": "STATUS", "_count": 1, "_repCode": 19, "_units": "", "_value": "IN-PROGRESS"}, {"_label": "INPUT-CHANNELS", "_count": 1, "_repCode": 23, "_units": "", "_value": {"origin": 11, "copy": 0, "identifier": "CURVE 1 CHANNEL"}}, {"_label": "OUTPUT-CHANNELS", "_count": 1, "_repCode": 23, "_units": "", "_value": {"origin": 11, "copy": 0, "identifier": "CURVE 2 CHANNEL"}}, {"_label": "INPUT-COMPUTATIONS", "_count": 1, "_repCode": 23, "_units": "", "_value": {"origin": 11, "copy": 0, "identifier": "computation_1 OBJ NAME"}}, {"_label": "OUTPUT-COMPUTATIONS", "_count": 1, "_repCode": 23, "_units": "", "_value": {"origin": 11, "copy": 0, "identifier": "computation_2 OBJ NAME"}}, {"_label": "PARAMETERS", "_count": 1, "_repCode": 23, "_units": "", "_value": {"origin": 11, "copy": 0, "identifier": "parameter_1-OBJ-NAME"}}, {"_label": "COMMENTS", "_count": 1, "_repCode": 20, "_units": "", "_value": "These are dummy values for testing"}]}}, {"Process": {"_name": {"origin": 11, "copy": 0, "identifier": "PROC-3 OBJ-NAME"}, "_attributes": [{"_label": "DESCRIPTION", "_count": 1, "_repCode": 20, "_units": "", "_value": "Process 3"}, {"_label": "TRADEMARK-NAME", "_count": 1, "_repCode": 20, "_units": "", "_value": "Proc 3 TMN"}, {"_label": "VERSION", "_count": 1, "_repCode": 20, "_units": "", "_value": "3.0.0"}, {"_label": "PROPERTIES", "_count": 1, "_repCode": 19, "_units": "", "_value": "PROP-3"}, {"_label": "STATUS", "_count": 1, "_repCode": 19, "_units": "", "_value": "ABORTED"}, {"_label": "INPUT-CHANNELS", "_count": 1, "_repCode": 23, "_units": "", "_value": {"origin": 11, "copy": 0, "identifier": "DEPTH CHANNEL"}}, {"_label": "OUTPUT-CHANNELS", "_count": 1, "_repCode": 23, "_units": "", "_value": {"origin": 11, "copy": 0, "identifier": "CURVE 1 CHANNEL"}}, {"_label": "INPUT-COMPUTATIONS", "_count": 1, "_repCode": 23, "_units": "", "_value": {"origin": 11, "copy": 0, "identifier": "computation_1 OBJ NAME"}}, {"_label": "OUTPUT-COMPUTATIONS", "_count": 1, "_repCode": 23, "_units": "", "_value": {"origin": 11, "copy": 0, "identifier": "computation_2 OBJ NAME"}}, {"_label": "PARAMETERS", "_count": 3, "_repCode": 23, "_units": "", "_value": [{"origin": 11, "copy": 0, "identifier": "parameter_1-OBJ-NAME"}, {"origin": 11, "copy": 0, "identifier": "parameter_2-OBJ-NAME"}, {"origin": 11, "copy": 0, "identifier": "parameter_3-OBJ-NAME"}]}, {"_label": "COMMENTS", "_count": 1, "_repCode": 20, "_units": "", "_value": "These are dummy values for testing"}]}}]}}, {"StaticEFLR": {"setName": null, "setType": "CALIBRATION-MEASUREMENT", "template": {"attributeList": [{"_label": "PHASE", "_count": 1, "_repCode": 19, "_units": "", "_value": null}, {"_label": "MEASUREMENT-SOURCE", "_count": 1, "_repCode": 24, "_units": "", "_value": null}, {"_label": "TYPE", "_count": 1, "_repCode": 19, "_units": "", "_value": null}, {"_label": "DIMENSION", "_count": 1, "_repCode": 18, "_units": "", "_value": null}, {"_label": "AXIS", "_count": 1, "_repCode": 23, "_units": "", "_value": null}, {"_label": "MEASUREMENT", "_count": 1, "_repCode": 19, "_units": "", "_value": null}, {"_label": "SAMPLE-COUNT", "_count": 1, "_repCode": 19, "_units": "", "_value": null}, {"_label": "MAXIMUM-DEVIATION", "_count": 1, "_repCode": 19, "_units": "", "_value": null}, {"_label": "STANDARD-DEVIATION", "_count": 1, "_repCode": 19, "_units": "", "_value": null}, {"_label": "BEGIN-TIME", "_count": 1, "_repCode": 21, "_units": "", "_value": null}, {"_label": "DURATION", "_count": 1, "_repCode": 19, "_units": "", "_value": null}, {"_label": "REFERENCE", "_count": 1, "_repCode": 19, "_units": "", "_value": null}, {"_label": "STANDARD", "_count": 1, "_repCode": 19, "_units": "", "_value": null}, {"_label": "PLUS-TOLERANCE", "_count": 1, "_repCode": 19, "_units": "", "_value": null}, {"_label": "MINUS-TOLERANCE", "_count": 1, "_repCode": 19, "_units": "", "_value": null}]}, "objects": [{"CalibrationMeasurement": {"_name": {"origin": 11, "copy": 0, "identifier": "calibration_measurement_1 OBJ-NAME"}, "_attributes": [{"_label": "PHASE", "_count": 1, "_repCode": 19, "_units": "", "_value": "BEFORE"}, {"_label": "MEASUREMENT-SOURCE", "_count": 1, "_repCode": 24, "_units": "", "_value": {"type": "CHANNEL", "origin": 11, "copy": 0, "identifier": "DEPTH CHANNEL"}}, {"_label": "TYPE", "_count": 1, "_repCode": 19, "_units": "", "_value": "Plus"}, {"_label": "DIMENSION", "_count": 1, "_repCode": 18, "_units": "", "_value": 1}, {"_label": "AXIS", "_count": 1, "_repCode": 23, "_units": "", "_value": null}, {"_label": "MEASUREMENT", "_count": 1, "_repCode": 7, "_units": "", "_value": 12.2323}, {"_label": "SAMPLE-COUNT", "_count": 1, "_repCode": 18, "_units": "", "_value": 12}, {"_label": "MAXIMUM-DEVIATION", "_count": 1, "_repCode": 7, "_units": "", "_value": 2.2324}, {"_label": "STANDARD-DEVIATION", "_count": 1, "_repCode": 7, "_units": "", "_value": 1.123}, {"_label": "BEGIN-TIME", "_count": 1, "_repCode": 21, "_units": "", "_value": {"time": "2022-09-06 19:08:33.963000", "tzone": {"timezone": "LocalStandard"}}}, {"_label": "DURATION", "_count": 1, "_repCode": 15, "_units": "s", "_value": 15}, {"_label": "REFERENCE", "_count": 1, "_repCode": 15, "_units": "", "_value": 11}, {"_label": "STANDARD", "_count": 1, "_repCode": 7, "_units": "", "_value": 11.2}, {"_label": "PLUS-TOLERANCE", "_count": 1, "_repCode": 7, "_units": "", "_value": 2.0}, {"_label": "MINUS-TOLERANCE", "_count": 1, "_repCode": 7, "_units": "", "_value": 1.0}]}}, {"CalibrationMeasurement": {"_name": {"origin": 11, "copy": 0, "identifier": "calibration_measurement_2 OBJ-NAME"}, "_attributes": [{"_label": "PHASE", "_count": 1, "_repCode": 19, "_units": "", "_value": "AFTER"}, {"_label": "MEASUREMENT-SOURCE", "_count": 1, "_repCode": 24, "_units": "", "_value": {"type": "CHANNEL", "origin": 11, "copy": 0, "identifier": "CURVE 1 CHANNEL"}}, {"_label": "TYPE", "_count": 1, "_repCode": 19, "_units": "", "_value": "Zero"}, {"_label": "DIMENSION", "_count": 1, "_repCode": 18, "_units": "", "_value": 1}, {"_label": "AXIS", "_count": 1, "_repCode": 23, "_units": "", "_value": null}, {"_label": "MEASUREMENT", "_count": 1, "_repCode": 7, "_units": "", "_value": 12.2323}, {"_label": "SAMPLE-COUNT", "_count": 1, "_repCode": 18, "_units": "", "_value": 12}, {"_label": "MAXIMUM-DEVIATION", "_count": 1, "_repCode": 7, "_units": "", "_value": 2.2324}, {"_label": "STANDARD-DEVIATION", "_count": 1, "_repCode": 7, "_units": "", "_value": 1.123}, {"_label": "BEGIN-TIME", "_count": 1, "_repCode": 21, "_units": "", "_value": {"time": "2022-09-06 19:08:33.963000", "tzone": {"timezone": "LocalStandard"}}}, {"_label": "DURATION", "_count": 1, "_repCode": 15, "_units": "s", "_value": 20}, {"_label": "REFERENCE", "_count": 1, "_repCode": 15, "_units": "", "_value": 11}, {"_label": "STANDARD", "_count": 1, "_repCode": 7, "_units": "", "_value": 11.2}, {"_label": "PLUS-TOLERANCE", "_count": 1, "_repCode": 7, "_units": "", "_value": 2.0}, {"_label": "MINUS-TOLERANCE", "_count": 1, "_repCode": 7, "_units": "", "_value": 1.0}]}}]}}, {"StaticEFLR": {"setName": null, "setType": "CALIBRATION-COEFFICIENT", "template": {"attributeList": [{"_label": "LABEL", "_count": 1, "_repCode": 19, "_units": "", "_value": null}, {"_label": "COEFFICIENTS", "_count": 1, "_repCode": 19, "_units": "", "_value": null}, {"_label": "REFERENCES", "_count": 1, "_repCode": 19, "_units": "", "_value": null}, {"_label": "PLUS-TOLERANCES", "_count": 1, "_repCode": 19, "_units": "", "_value": null}, {"_label": "MINUS-TOLERANCES", "_count": 1, "_repCode": 19, "_units": "", "_value": null}]}, "objects": [{"CalibrationCoefficient": {"_name": {"origin": 11, "copy": 0, "identifier": "calibration_coefficient_1 OBJ NAME"}, "_attributes": [{"_label": "LABEL", "_count": 1, "_repCode": 19, "_units": "", "_value": "COEF-1"}, {"_label": "COEFFICIENTS", "_count": 3, "_repCode": 7, "_units": "", "_value": [12.12, 34.34, 14.23]}, {"_label": "REFERENCES", "_count": 3, "_repCode": 7, "_units": "", "_value": [11.0, 32.2, 15.542]}, {"_label": "PLUS-TOLERANCES", "_count": 3, "_repCode": 7, "_units": "", "_value": [1.2, 3.6, 2.023]}, {"_label": "MINUS-TOLERANCES", "_count": 3, "_repCode": 7, "_units": "", "_value": [0.98, 2.89, 1.978]}]}}, {"CalibrationCoefficient": {"_name": {"origin": 11, "copy": 0, "identifier": "calibration_coefficient_2 OBJ NAME"}, "_attributes": [{"_label": "LABEL", "_count": 1, "_repCode": 19, "_units": "", "_value": "COEF-2"}, {"_label": "COEFFICIENTS", "_count": 3, "_repCode": 7, "_units": "", "_value": [12.12, 34.34, 14.23]}, {"_label": "REFERENCES", "_count": 3, "_repCode": 7, "_units": "", "_value": [11.0, 32.2, 15.542]}, {"_label": "PLUS-TOLERANCES", "_count": 3, "_repCode": 7, "_units": "", "_value": [1.2, 3.6, 2.023]}, {"_label": "MINUS-TOLERANCES", "_count": 3, "_repCode": 7, "_units": "", "_value": [0.98, 2.89, 1.978]}]}}]}}]}